LICENSE
MANIFEST.in
NOTICE
README.md
VERSION
setup.cfg
setup.py
sagemaker_training.egg-info/PKG-INFO
sagemaker_training.egg-info/SOURCES.txt
sagemaker_training.egg-info/dependency_links.txt
sagemaker_training.egg-info/entry_points.txt
sagemaker_training.egg-info/requires.txt
sagemaker_training.egg-info/top_level.txt
src/sagemaker_training/__init__.py
src/sagemaker_training/_entry_point_type.py
src/sagemaker_training/content_types.py
src/sagemaker_training/encoders.py
src/sagemaker_training/entry_point.py
src/sagemaker_training/environment.py
src/sagemaker_training/errors.py
src/sagemaker_training/files.py
src/sagemaker_training/functions.py
src/sagemaker_training/intermediate_output.py
src/sagemaker_training/logging_config.py
src/sagemaker_training/mapping.py
src/sagemaker_training/modules.py
src/sagemaker_training/mpi.py
src/sagemaker_training/params.py
src/sagemaker_training/process.py
src/sagemaker_training/pytorch_xla.py
src/sagemaker_training/record_pb2.py
src/sagemaker_training/recordio.py
src/sagemaker_training/runner.py
src/sagemaker_training/smdataparallel.py
src/sagemaker_training/timeout.py
src/sagemaker_training/torch_distributed.py
src/sagemaker_training/trainer.py
src/sagemaker_training/c/gethostname.c
src/sagemaker_training/c/jsmn.c
src/sagemaker_training/c/jsmn.h
src/sagemaker_training/cli/__init__.py
src/sagemaker_training/cli/train.py